packio/__init__.py
packio/io.py
packio/zipping.py
packio-0.1.2.dist-info/licenses/LICENSE
packio-0.1.2.dist-info/METADATA
packio-0.1.2.dist-info/WHEEL
packio-0.1.2.dist-info/top_level.txt
packio-0.1.2.dist-info/RECORD
