Metadata-Version: 2.4
Name: packio
Version: 0.1.2
Summary: IO for multiple python objects to/from a single file
Author-email: Zach Kurtz <zkurtz@gmail.com>
Project-URL: Source, https://github.com/zkurtz/packio
Requires-Python: >=3.10
License-File: LICENSE
Dynamic: license-file
